webargs/__init__.py
webargs/aiohttpparser.py
webargs/asyncparser.py
webargs/bottleparser.py
webargs/core.py
webargs/djangoparser.py
webargs/falconparser.py
webargs/fields.py
webargs/flaskparser.py
webargs/multidictproxy.py
webargs/py.typed
webargs/pyramidparser.py
webargs/testing.py
webargs/tornadoparser.py
webargs-8.4.0.dist-info/LICENSE
webargs-8.4.0.dist-info/METADATA
webargs-8.4.0.dist-info/WHEEL
webargs-8.4.0.dist-info/top_level.txt
webargs-8.4.0.dist-info/RECORD
