Metadata-Version: 2.1
Name: webargs
Version: 8.4.0
Summary: Declarative parsing and validation of HTTP request objects, with built-in support for popular web frameworks, including Flask, Django, Bottle, Tornado, Pyramid, Falcon, and aiohttp.
Home-page: https://github.com/marshmallow-code/webargs
Author: Steven Loria
Author-email: sloria1@gmail.com
License: MIT
Project-URL: Changelog, https://webargs.readthedocs.io/en/latest/changelog.html
Project-URL: Issues, https://github.com/marshmallow-code/webargs/issues
Project-URL: Funding, https://opencollective.com/marshmallow
Project-URL: Tidelift, https://tidelift.com/subscription/pkg/pypi-webargs?utm_source=pypi-marshmallow&utm_medium=pypi
Keywords: webargs,http,flask,django,bottle,tornado,aiohttp,request,arguments,validation,parameters,rest,api,marshmallow
Classifier: Development Status :: 5 - Production/Stable
Classifier: Intended Audience :: Developers
Classifier: License :: OSI Approved :: MIT License
Classifier: Natural Language :: English
Classifier: Programming Language :: Python :: 3
Classifier: Programming Language :: Python :: 3.7
Classifier: Programming Language :: Python :: 3.8
Classifier: Programming Language :: Python :: 3.9
Classifier: Programming Language :: Python :: 3.10
Classifier: Programming Language :: Python :: 3.11
Classifier: Programming Language :: Python :: 3 :: Only
Classifier: Topic :: Internet :: WWW/HTTP :: Dynamic Content
Classifier: Topic :: Internet :: WWW/HTTP :: WSGI :: Application
Requires-Python: >=3.8
License-File: LICENSE
Requires-Dist: marshmallow>=3.0.0
Requires-Dist: packaging
Provides-Extra: frameworks
Requires-Dist: Flask>=0.12.5; extra == "frameworks"
Requires-Dist: Django>=2.2.0; extra == "frameworks"
Requires-Dist: bottle>=0.12.13; extra == "frameworks"
Requires-Dist: tornado>=4.5.2; extra == "frameworks"
Requires-Dist: pyramid>=1.9.1; extra == "frameworks"
Requires-Dist: falcon>=2.0.0; extra == "frameworks"
Requires-Dist: aiohttp>=3.0.8; extra == "frameworks"
Provides-Extra: tests
Requires-Dist: pytest; extra == "tests"
Requires-Dist: pytest-asyncio; extra == "tests"
Requires-Dist: webtest==3.0.0; extra == "tests"
Requires-Dist: webtest-aiohttp==2.0.0; extra == "tests"
Requires-Dist: pytest-aiohttp>=0.3.0; extra == "tests"
Requires-Dist: Flask>=0.12.5; extra == "tests"
Requires-Dist: Django>=2.2.0; extra == "tests"
Requires-Dist: bottle>=0.12.13; extra == "tests"
Requires-Dist: tornado>=4.5.2; extra == "tests"
Requires-Dist: pyramid>=1.9.1; extra == "tests"
Requires-Dist: falcon>=2.0.0; extra == "tests"
Requires-Dist: aiohttp>=3.0.8; extra == "tests"
Provides-Extra: lint
Requires-Dist: mypy==1.8.0; extra == "lint"
Requires-Dist: flake8==7.0.0; extra == "lint"
Requires-Dist: flake8-bugbear==23.12.2; extra == "lint"
Requires-Dist: pre-commit<4.0,>=2.4; extra == "lint"
Provides-Extra: docs
Requires-Dist: Sphinx==7.2.6; extra == "docs"
Requires-Dist: sphinx-issues==3.0.1; extra == "docs"
Requires-Dist: furo==2023.9.10; extra == "docs"
Requires-Dist: Flask>=0.12.5; extra == "docs"
Requires-Dist: Django>=2.2.0; extra == "docs"
Requires-Dist: bottle>=0.12.13; extra == "docs"
Requires-Dist: tornado>=4.5.2; extra == "docs"
Requires-Dist: pyramid>=1.9.1; extra == "docs"
Requires-Dist: falcon>=2.0.0; extra == "docs"
Requires-Dist: aiohttp>=3.0.8; extra == "docs"
Provides-Extra: dev
Requires-Dist: pytest; extra == "dev"
Requires-Dist: pytest-asyncio; extra == "dev"
Requires-Dist: webtest==3.0.0; extra == "dev"
Requires-Dist: webtest-aiohttp==2.0.0; extra == "dev"
Requires-Dist: pytest-aiohttp>=0.3.0; extra == "dev"
Requires-Dist: Flask>=0.12.5; extra == "dev"
Requires-Dist: Django>=2.2.0; extra == "dev"
Requires-Dist: bottle>=0.12.13; extra == "dev"
Requires-Dist: tornado>=4.5.2; extra == "dev"
Requires-Dist: pyramid>=1.9.1; extra == "dev"
Requires-Dist: falcon>=2.0.0; extra == "dev"
Requires-Dist: aiohttp>=3.0.8; extra == "dev"
Requires-Dist: mypy==1.8.0; extra == "dev"
Requires-Dist: flake8==7.0.0; extra == "dev"
Requires-Dist: flake8-bugbear==23.12.2; extra == "dev"
Requires-Dist: pre-commit<4.0,>=2.4; extra == "dev"
Requires-Dist: tox; extra == "dev"
